pyAlice/__init__.py
pyAlice/base.py
pyAlice/functions.py
pyAlice/key_word.py
pyAlice/py_alice.py
pyAlice/simulation.py
pyAlice/errors/errors.py
pyAlice/messages/embedded_message.py
pyAlice/messages/errors_messages.py
pyaliceya-0.2.1.dist-info/METADATA
pyaliceya-0.2.1.dist-info/WHEEL
pyaliceya-0.2.1.dist-info/top_level.txt
pyaliceya-0.2.1.dist-info/RECORD
